{
  "events": [
    {
      "id": "ma-joint-muni-regional-2025-12-17",
      "name": "Joint Committee on Municipalities and Regional Government",
      "date": "2025-12-17T20:00:00.000Z",
      "time": "3:00 PM",
      "location": "Written Testimony Only",
      "committee": "Joint Committee on Municipalities and Regional Government",
      "type": "committee-hearing",
      "level": "state",
      "state": "MA",
      "city": "Boston",
      "lat": 42.3601,
      "lng": -71.0589,
      "zipCode": null,
      "description": "Massachusetts legislative event",
      "sourceUrl": "https://malegislature.gov/Events/Hearings/Detail/5516",
      "bills": [
        {
          "id": "H.4784",
          "title": "An Act providing for a town administrator in the town of Hopedale",
          "url": "https://malegislature.gov/Bills/194/H.4784"
        },
        {
          "id": "H.4795",
          "title": "An Act amending the charter for the town of Groton",
          "url": "https://malegislature.gov/Bills/194/H.4795"
        }
      ]
    },
    {
      "id": "ma-senate-ways-means-2025-12-17",
      "name": "Senate Committee on Ways and Means",
      "date": "2025-12-17T21:00:00.000Z",
      "time": "4:00 PM",
      "location": "Written Testimony Only",
      "committee": "Senate Committee on Ways and Means",
      "type": "committee-hearing",
      "level": "state",
      "state": "MA",
      "city": "Boston",
      "lat": 42.3601,
      "lng": -71.0589,
      "zipCode": null,
      "description": "Massachusetts legislative event",
      "sourceUrl": "https://malegislature.gov/Events/Hearings/Detail/5518",
      "bills": []
    }
  ],
  "count": 2,
  "billsCount": 2,
  "lastUpdated": "2025-12-17T00:00:00.000Z"
}
